blosc-1.11.4.data/data/include/blosc-export.h
blosc-1.11.4.data/data/include/blosc.h
blosc-1.11.4.data/data/lib/libblosc.1.dylib
blosc-1.11.4.data/data/lib/libblosc.dylib
blosc-1.11.4.data/data/lib/libblosc.1.21.7.dylib
blosc-1.11.4.data/data/lib/libblosc.a
blosc-1.11.4.data/data/lib/pkgconfig/blosc.pc
blosc/version.py
blosc/toplevel.py
blosc/_version.py
blosc/__init__.py
blosc/test.py
blosc/blosc_extension.cpython-311-darwin.so
blosc-1.11.4.dist-info/RECORD
blosc-1.11.4.dist-info/WHEEL
blosc-1.11.4.dist-info/top_level.txt
blosc-1.11.4.dist-info/METADATA
blosc-1.11.4.dist-info/licenses/LICENSE.txt
